fast_forecast/__init__.py
fast_forecast/mco_forecast.py
fast_forecast-0.1.0.dist-info/METADATA
fast_forecast-0.1.0.dist-info/WHEEL
fast_forecast-0.1.0.dist-info/top_level.txt
fast_forecast-0.1.0.dist-info/RECORD
