Metadata-Version: 2.4
Name: fast_forecast
Version: 0.1.0
Summary: Modelos rápidos de pronóstico lineal con tendencia, estacionalidad, LOWESS y variables exógenas.
Author-email: Sergio Pedro Diaz Paredes <sdiazp@labdatosperu.org>
License: MIT
Project-URL: Homepage, https://github.com/sdiazpy/fast_forecast
Requires-Python: >=3.8
Requires-Dist: numpy
Requires-Dist: pandas
Requires-Dist: scikit-learn
Requires-Dist: statsmodels
